Metadata-Version: 2.1
Name: cloudquicklabs1
Version: 0.0.4
Summary: An application that informs you of the time in different locations and timezones
Home-page: https://www.youtube.com/channel/UCv9MUffHWyo2GgLIDLVu0KQ
Author: Rekhu Chinnarathod
Author-email: vrchinnarathod@gmail.com
License: UNKNOWN
Platform: UNKNOWN
Classifier: Programming Language :: Python :: 3
Classifier: License :: OSI Approved :: MIT License
Classifier: Operating System :: OS Independent
